azure/mgmt/connectedvmware/__init__.py
azure/mgmt/connectedvmware/_configuration.py
azure/mgmt/connectedvmware/_connected_vmware_mgmt_client.py
azure/mgmt/connectedvmware/_patch.py
azure/mgmt/connectedvmware/_serialization.py
azure/mgmt/connectedvmware/_vendor.py
azure/mgmt/connectedvmware/_version.py
azure/mgmt/connectedvmware/py.typed
azure/mgmt/connectedvmware/aio/__init__.py
azure/mgmt/connectedvmware/aio/_configuration.py
azure/mgmt/connectedvmware/aio/_connected_vmware_mgmt_client.py
azure/mgmt/connectedvmware/aio/_patch.py
azure/mgmt/connectedvmware/aio/operations/__init__.py
azure/mgmt/connectedvmware/aio/operations/_clusters_operations.py
azure/mgmt/connectedvmware/aio/operations/_datastores_operations.py
azure/mgmt/connectedvmware/aio/operations/_hosts_operations.py
azure/mgmt/connectedvmware/aio/operations/_inventory_items_operations.py
azure/mgmt/connectedvmware/aio/operations/_operations.py
azure/mgmt/connectedvmware/aio/operations/_patch.py
azure/mgmt/connectedvmware/aio/operations/_resource_pools_operations.py
azure/mgmt/connectedvmware/aio/operations/_vcenters_operations.py
azure/mgmt/connectedvmware/aio/operations/_virtual_machine_instances_operations.py
azure/mgmt/connectedvmware/aio/operations/_virtual_machine_templates_operations.py
azure/mgmt/connectedvmware/aio/operations/_virtual_networks_operations.py
azure/mgmt/connectedvmware/aio/operations/_vm_instance_guest_agents_operations.py
azure/mgmt/connectedvmware/aio/operations/_vm_instance_hybrid_identity_metadata_operations.py
azure/mgmt/connectedvmware/models/__init__.py
azure/mgmt/connectedvmware/models/_connected_vmware_mgmt_client_enums.py
azure/mgmt/connectedvmware/models/_models_py3.py
azure/mgmt/connectedvmware/models/_patch.py
azure/mgmt/connectedvmware/operations/__init__.py
azure/mgmt/connectedvmware/operations/_clusters_operations.py
azure/mgmt/connectedvmware/operations/_datastores_operations.py
azure/mgmt/connectedvmware/operations/_hosts_operations.py
azure_mgmt_connectedvmware-1.0.0.dist-info/LICENSE
azure_mgmt_connectedvmware-1.0.0.dist-info/METADATA
azure_mgmt_connectedvmware-1.0.0.dist-info/WHEEL
azure_mgmt_connectedvmware-1.0.0.dist-info/top_level.txt
azure_mgmt_connectedvmware-1.0.0.dist-info/RECORD
